napari_kics/__init__.py
napari_kics/global_signals.py
napari_kics/widget_loader.py
napari_kics/analysis_plots/__init__.py
napari_kics/analysis_plots/__main__.py
napari_kics/analysis_plots/resources/data/mMyoMyo.estimates.tsv
napari_kics/analysis_plots/resources/data/mMyoMyo.fasta.fai
napari_kics/models/__init__.py
napari_kics/models/estimates_table_model.py
napari_kics/resources/artwork/logo.svg
napari_kics/resources/data/mHomSap_male.fasta.fai
napari_kics/resources/data/mHomSap_male.jpeg
napari_kics/utils/__init__.py
napari_kics/utils/export_annotated_karyotype.py
napari_kics/utils/guess_chromosome_labels.py
napari_kics/utils/history_debug.py
napari_kics/utils/label_history_processor.py
napari_kics/widgets/__init__.py
napari_kics/widgets/analysis_widget.py
napari_kics/widgets/annotation_widget.py
napari_kics/widgets/clickable_line_edit.py
napari_kics/widgets/head_layout.py
napari_kics/widgets/input_double_slider.py
napari_kics/widgets/karyotype_widget.py
napari_kics/widgets/label_widget.py
napari_kics/widgets/order_widget.py
napari_kics/widgets/preprocessing_widget.py
napari_kics/widgets/saving_widget.py
napari_kics-0.0.3rc6.dist-info/LICENSE
napari_kics-0.0.3rc6.dist-info/METADATA
napari_kics-0.0.3rc6.dist-info/WHEEL
napari_kics-0.0.3rc6.dist-info/entry_points.txt
napari_kics-0.0.3rc6.dist-info/top_level.txt
napari_kics-0.0.3rc6.dist-info/RECORD
