Metadata-Version: 2.1
Name: napari-kics
Version: 0.0.3rc6
Summary: A plugin to estimate chromosome sizes from karyotype images.
Author: Alexandr Dibrov
Author-email: dibrov@mpi-cbg.de
License: BSD-3-Clause
Classifier: Development Status :: 2 - Pre-Alpha
Classifier: Intended Audience :: Developers
Classifier: Framework :: napari
Classifier: Topic :: Scientific/Engineering :: Image Processing
Classifier: Topic :: Scientific/Engineering :: Information Analysis
Classifier: Programming Language :: Python
Classifier: Programming Language :: Python :: 3
Classifier: Programming Language :: Python :: 3.7
Classifier: Programming Language :: Python :: 3.8
Classifier: Programming Language :: Python :: 3.9
Classifier: Operating System :: OS Independent
Classifier: License :: OSI Approved :: BSD License
Requires-Python: >=3.7
License-File: LICENSE
Requires-Dist: napari-plugin-engine (>=0.1.4)
Requires-Dist: numpy
Requires-Dist: napari[all]
Requires-Dist: scikit-image
Requires-Dist: pandas
Requires-Dist: pulp
Requires-Dist: pyqtgraph
